django_guts
